hashsigs/__init__.py
hashsigs/_rust.pyi
hashsigs/core.py
hashsigs/py.typed
hashsigs-0.0.2.dist-info/licenses/COPYING
hashsigs-0.0.2.dist-info/METADATA
hashsigs-0.0.2.dist-info/WHEEL
hashsigs-0.0.2.dist-info/top_level.txt
hashsigs-0.0.2.dist-info/RECORD
