Metadata-Version: 2.4
Name: hashsigs
Version: 0.0.2
Summary: WOTS+ hash-based signatures in Python with optional Rust acceleration
Author-email: "Richard T. Carback III" <rick.rust.cargo.383d5@passmail.net>
License:                     GNU AFFERO GENERAL PUBLIC LICENSE
Project-URL: Homepage, https://github.com/quipnetwork/hashsigs-py
Project-URL: Repository, https://github.com/quipnetwork/hashsigs-py
Project-URL: Documentation, https://docs.rs/hashsigs-rs
Keywords: cryptography,wots,signature,wots+,hash-based
Classifier: Programming Language :: Python :: 3
Classifier: Programming Language :: Python :: 3 :: Only
Classifier: Programming Language :: Python :: 3.8
Classifier: Programming Language :: Python :: 3.9
Classifier: Programming Language :: Python :: 3.10
Classifier: Programming Language :: Python :: 3.11
Classifier: Programming Language :: Python :: 3.12
Classifier: Programming Language :: Python :: 3.13
Classifier: Programming Language :: Rust
Classifier: Topic :: Security :: Cryptography
Requires-Python: >=3.8
License-File: COPYING
Provides-Extra: rust
Requires-Dist: setuptools-rust>=1.9.0; extra == "rust"
Provides-Extra: dev
Requires-Dist: pytest; extra == "dev"
Requires-Dist: pytest-cov; extra == "dev"
Requires-Dist: tox>=4; extra == "dev"
Requires-Dist: flake8>=6; extra == "dev"
Requires-Dist: mypy>=1.7; extra == "dev"
Requires-Dist: ruff>=0.4; extra == "dev"
Requires-Dist: pycryptodome; extra == "dev"
Dynamic: license-file
